pyworkflow/__init__.py
pyworkflow/_version.py
pyworkflow/config.py
pyworkflow/constants.py
pyworkflow/exceptions.py
pyworkflow/object.py
pyworkflow/plugin.py
pyworkflow/template.py
pyworkflow/viewer.py
pyworkflow/wizard.py
pyworkflow/apps/__init__.py
pyworkflow/apps/pw_manager.py
pyworkflow/apps/pw_plot.py
pyworkflow/apps/pw_project.py
pyworkflow/apps/pw_protocol_list.py
pyworkflow/apps/pw_protocol_run.py
pyworkflow/apps/pw_run_tests.py
pyworkflow/apps/pw_schedule_run.py
pyworkflow/apps/pw_sleep.py
pyworkflow/apps/pw_sync_data.py
pyworkflow/apps/pw_viewer.py
pyworkflow/gui/__init__.py
pyworkflow/gui/browser.py
pyworkflow/gui/canvas.py
pyworkflow/gui/dialog.py
pyworkflow/gui/form.py
pyworkflow/gui/graph.py
pyworkflow/gui/graph_layout.py
pyworkflow/gui/gui.py
pyworkflow/gui/matplotlib_image.py
pyworkflow/gui/plotter.py
pyworkflow/gui/text.py
pyworkflow/gui/tooltip.py
pyworkflow/gui/tree.py
pyworkflow/gui/widgets.py
pyworkflow/gui/no-tkinter/_tkinter.py
pyworkflow/gui/project/__init__.py
pyworkflow/gui/project/base.py
pyworkflow/gui/project/constants.py
pyworkflow/gui/project/labels.py
pyworkflow/gui/project/project.py
pyworkflow/gui/project/searchprotocol.py
pyworkflow/gui/project/searchrun.py
pyworkflow/gui/project/steps.py
pyworkflow/gui/project/utils.py
pyworkflow/gui/project/variables.py
pyworkflow/gui/project/viewdata.py
pyworkflow/gui/project/viewprojects.py
pyworkflow/gui/project/viewprotocols.py
pyworkflow/gui/project/viewprotocols_extra.py
pyworkflow/mapper/__init__.py
pyworkflow/mapper/mapper.py
pyworkflow/mapper/sqlite.py
pyworkflow/mapper/sqlite_db.py
pyworkflow/project/__init__.py
pyworkflow/project/config.py
pyworkflow/project/manager.py
pyworkflow/project/project.py
pyworkflow/project/scripts/clean_projects.py
pyworkflow/project/scripts/config.py
pyworkflow/project/scripts/create.py
pyworkflow/project/scripts/edit_workflow.py
pyworkflow/project/scripts/fix_links.py
pyworkflow/project/scripts/load.py
pyworkflow/project/scripts/refresh.py
scipion_pyworkflow_windows-0.1.0.dist-info/METADATA
scipion_pyworkflow_windows-0.1.0.dist-info/WHEEL
scipion_pyworkflow_windows-0.1.0.dist-info/entry_points.txt
scipion_pyworkflow_windows-0.1.0.dist-info/licenses/LICENSE.txt
scipion_pyworkflow_windows-0.1.0.dist-info/RECORD
