Metadata-Version: 2.3
Name: scipion-pyworkflow-windows
Version: 0.1.0
Summary: Simple workflow platform used in scientific applications, initially developed within the Scipion framework for image processing in Electron Microscopy. Fork of the project to support windows.
Project-URL: Homepage, https://github.com/scipion-em/scipion-pyworkflow
Project-URL: Bug Reports, https://github.com/scipion-em/scipion-pyworkflow/issues
Project-URL: Source, https://github.com/scipion-em/scipion-pyworkflow/
Author-email: "J.M. De la Rosa Trevin" <delarosatrevin@scilifelab.se>, Roberto Marabini <roberto@cnb.csic.es>, Grigory Sharov <gsharov@mrc-lmb.cam.ac.uk>, Josue Gomez Blanco <josue.gomez-blanco@mcgill.ca>, Pablo Conesa <pconesa@cnb.csic.es>, Yunior Fonseca Reyna <fonsecareyna@cnb.csic.es>
Keywords: cryo-em,electron-microscopy,image-processing,science,scipion,structural-biology,workflows
Classifier: Development Status :: 5 - Production/Stable
Classifier: Intended Audience :: Science/Research
Classifier: License :: OSI Approved :: GNU General Public License v3 (GPLv3)
Classifier: Programming Language :: Python :: 3.8
Classifier: Programming Language :: Python :: 3.9
Classifier: Programming Language :: Python :: 3.10
Classifier: Programming Language :: Python :: 3.11
Classifier: Programming Language :: Python :: 3.12
Classifier: Topic :: Scientific/Engineering
Requires-Python: >=3.8
Requires-Dist: bibtexparser
Requires-Dist: configparser
Requires-Dist: distro
Requires-Dist: importlib-metadata
Requires-Dist: matplotlib
Requires-Dist: numpy
Requires-Dist: pillow
Requires-Dist: psutil
Requires-Dist: requests
Requires-Dist: tkcolorpicker
